rodder/__init__.py
rodder/rodder.py
rodder-0.1.9.1.dist-info/LICENSE
rodder-0.1.9.1.dist-info/WHEEL
rodder-0.1.9.1.dist-info/METADATA
rodder-0.1.9.1.dist-info/RECORD
