Metadata-Version: 2.1
Name: rodder
Version: 0.1.9.1
Summary: A distro-independant package manager for Linux
Home-page: https://github.com/Ruthenic/rodder
License: Unlicense
Author: Drake
Author-email: mdrakea3@tutanota.com
Requires-Python: >=3.8,<4.0
Classifier: License :: Other/Proprietary License
Classifier: Programming Language :: Python :: 3
Classifier: Programming Language :: Python :: 3.8
Classifier: Programming Language :: Python :: 3.9
Project-URL: Repository, https://github.com/Ruthenic/rodder
